{
  "main": {
    "id": "198923174aa85c06",
    "type": "split",
    "children": [
      {
        "id": "b31593c473150f6c",
        "type": "tabs",
        "children": [
          {
            "id": "5170bec5267104c9",
            "type": "leaf",
            "state": {
              "type": "markdown",
              "state": {
                "file": "docs/как работают классы.md",
                "mode": "source",
                "source": false
              },
              "icon": "lucide-file",
              "title": "как работают классы"
            }
          }
        ]
      }
    ],
    "direction": "vertical"
  },
  "left": {
    "id": "99ccc462be033a15",
    "type": "split",
    "children": [
      {
        "id": "8f5dc08543205acf",
        "type": "tabs",
        "children": [
          {
            "id": "bcdc3d05bf0afd33",
            "type": "leaf",
            "state": {
              "type": "file-explorer",
              "state": {
                "sortOrder": "alphabetical",
                "autoReveal": false
              },
              "icon": "lucide-folder-closed",
              "title": "Файловый менеджер"
            }
          },
          {
            "id": "d363516b4d5e0fe3",
            "type": "leaf",
            "state": {
              "type": "search",
              "state": {
                "query": "tag:#RU",
                "matchingCase": false,
                "explainSearch": false,
                "collapseAll": false,
                "extraContext": false,
                "sortOrder": "alphabetical"
              },
              "icon": "lucide-search",
              "title": "Поиск"
            }
          },
          {
            "id": "18770ebd9ee578bc",
            "type": "leaf",
            "state": {
              "type": "bookmarks",
              "state": {},
              "icon": "lucide-bookmark",
              "title": "Закладки"
            }
          }
        ],
        "currentTab": 1
      }
    ],
    "direction": "horizontal",
    "width": 300
  },
  "right": {
    "id": "4b619107cae6a8e0",
    "type": "split",
    "children": [
      {
        "id": "f45796a37ff5d142",
        "type": "tabs",
        "children": [
          {
            "id": "4a77777d41eb4f7e",
            "type": "leaf",
            "state": {
              "type": "backlink",
              "state": {
                "file": "docs/как работают классы.md",
                "collapseAll": false,
                "extraContext": false,
                "sortOrder": "alphabetical",
                "showSearch": false,
                "searchQuery": "",
                "backlinkCollapsed": false,
                "unlinkedCollapsed": true
              },
              "icon": "links-coming-in",
              "title": "Обратные ссылки для как работают классы"
            }
          },
          {
            "id": "28fc66529208cce7",
            "type": "leaf",
            "state": {
              "type": "outgoing-link",
              "state": {
                "file": "docs/как работают классы.md",
                "linksCollapsed": false,
                "unlinkedCollapsed": true
              },
              "icon": "links-going-out",
              "title": "Исходящие ссылки из как работают классы"
            }
          },
          {
            "id": "2d656e029f9911fe",
            "type": "leaf",
            "state": {
              "type": "tag",
              "state": {
                "sortOrder": "frequency",
                "useHierarchy": true,
                "showSearch": false,
                "searchQuery": ""
              },
              "icon": "lucide-tags",
              "title": "Теги"
            }
          },
          {
            "id": "e586039687934ed1",
            "type": "leaf",
            "state": {
              "type": "outline",
              "state": {
                "file": "docs/как работают классы.md",
                "followCursor": false,
                "showSearch": false,
                "searchQuery": ""
              },
              "icon": "lucide-list",
              "title": "Структура как работают классы"
            }
          }
        ]
      }
    ],
    "direction": "horizontal",
    "width": 300,
    "collapsed": true
  },
  "left-ribbon": {
    "hiddenItems": {
      "switcher:Меню быстрого перехода": false,
      "graph:Граф": false,
      "canvas:Создать новый холст": false,
      "daily-notes:Сегодняшняя заметка": false,
      "templates:Вставить шаблон": false,
      "command-palette:Открыть палитру команд": false
    }
  },
  "active": "d363516b4d5e0fe3",
  "lastOpenFiles": [
    "text.lua"
  ]
}